Workbook

Sheet Products
A1: Product_ID | B1: Category | C1: Product_Name | D1: Unit_Price | E1: Cost | F1: Margin_Pct | G1: Status
A2: P001 | B2: Electronics | C2: Laptop | D2: 1200 | E2: 850 | F2: =(D2-E2)/D2 | G2: Active
A3: P002 | B3: Electronics | C3: Phone | D3: 800 | E3: 520 | F3: =(D3-E3)/D3 | G3: Active
A4: P003 | B4: Furniture | C4: Desk | D4: 350 | E4: 200 | F4: =(D4-E4)/D4 | G4: Active
A5: P004 | B5: Furniture | C5: Chair | D5: 275 | E5: 160 | F5: =(D5-E5)/D5 | G5: Discontinued
A6: P005 | B6: Clothing | C6: Jacket | D6: 150 | E6: 80 | F6: =(D6-E6)/D6 | G6: Active
A7: P006 | B7: Clothing | C7: Shirt | D7: 45 | E7: 22 | F7: =(D7-E7)/D7 | G7: Active
A8: P007 | B8: Electronics | C8: Tablet | D8: 500 | E8: 310 | F8: =(D8-E8)/D8 | G8: Active
A9: P008 | B9: Furniture | C9: Bookshelf | D9: 180 | E9: 100 | F9: =(D9-E9)/D9 | G9: Active
A10: P009 | B10: Clothing | C10: Shoes | D10: 95 | E10: 50 | F10: =(D10-E10)/D10 | G10: Active
A11: P010 | B11: Electronics | C11: Monitor | D11: 450 | E11: 280 | F11: =(D11-E11)/D11 | G11: Active
A13: TOTALS | D13: =SUM(D2:D11) | E13: =SUM(E2:E11) | F13: =AVERAGE(F2:F11)
A14: AVG_PRICE | D14: =AVERAGE(D2:D11)
A15: MAX_PRICE | D15: =MAX(D2:D11)
A16: MIN_PRICE | D16: =MIN(D2:D11)
A17: ACTIVE_COUNT | D17: =COUNTIF(G2:G11,"Active")

Sheet Q1 Sales
A1: Date | B1: Product_ID | C1: Region | D1: Qty | E1: Unit_Price | F1: Revenue | G1: Discount_Pct | H1: Net_Revenue
A2: 2024-01-05 | B2: P001 | C2: North | D2: 3 | E2: 1200 | F2: =D2*E2 | G2: 0 | H2: =F2*(1-G2)
A3: 2024-01-12 | B3: P002 | C3: South | D3: 5 | E3: 800 | F3: =D3*E3 | G3: 0.05 | H3: =F3*(1-G3)
A4: 2024-01-20 | B4: P003 | C4: North | D4: 2 | E4: 350 | F4: =D4*E4 | G4: 0 | H4: =F4*(1-G4)
A5: 2024-02-03 | B5: P001 | C5: East | D5: 1 | E5: 1200 | F5: =D5*E5 | G5: 0.1 | H5: =F5*(1-G5)
A6: 2024-02-14 | B6: P005 | C6: West | D6: 10 | E6: 150 | F6: =D6*E6 | G6: 0 | H6: =F6*(1-G6)
A7: 2024-02-28 | B7: P006 | C7: North | D7: 20 | E7: 45 | F7: =D7*E7 | G7: 0 | H7: =F7*(1-G7)
A8: 2024-03-05 | B8: P001 | C8: South | D8: 4 | E8: 1200 | F8: =D8*E8 | G8: 0.05 | H8: =F8*(1-G8)
A9: 2024-03-15 | B9: P007 | C9: East | D9: 3 | E9: 500 | F9: =D9*E9 | G9: 0.1 | H9: =F9*(1-G9)
A10: 2024-03-22 | B10: P002 | C10: North | D10: 6 | E10: 800 | F10: =D10*E10 | G10: 0 | H10: =F10*(1-G10)
A11: 2024-01-08 | B11: P004 | C11: West | D11: 1 | E11: 275 | F11: =D11*E11 | G11: 0.15 | H11: =F11*(1-G11)
A12: 2024-01-25 | B12: P008 | C12: North | D12: 2 | E12: 180 | F12: =D12*E12 | G12: 0 | H12: =F12*(1-G12)
A13: 2024-02-10 | B13: P009 | C13: South | D13: 8 | E13: 95 | F13: =D13*E13 | G13: 0 | H13: =F13*(1-G13)
... A20: 2024-02-05 | B20: P007 | C20: North | D20: 1 | E20: 500 | F20: =D20*E20 | G20: 0.1 | H20: =F20*(1-G20)
A22: TOTAL_QTY | D22: =SUM(D2:D20)
A23: TOTAL_REVENUE | F23: =SUM(F2:F20)
A24: TOTAL_NET_REV | H24: =SUM(H2:H20)
A25: AVG_DISCOUNT | G25: =AVERAGE(G2:G20)
A26: NORTH_REVENUE | F26: =SUMIFS(F2:F20,C2:C20,"North")
A27: SOUTH_REVENUE | F27: =SUMIFS(F2:F20,C2:C20,"South")
A28: EAST_REVENUE | F28: =SUMIFS(F2:F20,C2:C20,"East")
A29: WEST_REVENUE | F29: =SUMIFS(F2:F20,C2:C20,"West")

Sheet Q2 Sales
A1: Date | B1: Product_ID | C1: Region | D1: Qty | E1: Unit_Price | F1: Revenue | G1: Discount_Pct | H1: Net_Revenue
A2: 2024-04-02 | B2: P001 | C2: South | D2: 2 | E2: 1200 | F2: =D2*E2 | G2: 0.05 | H2: =F2*(1-G2)
A3: 2024-04-15 | B3: P003 | C3: North | D3: 4 | E3: 350 | F3: =D3*E3 | G3: 0 | H3: =F3*(1-G3)
A4: 2024-04-22 | B4: P005 | C4: East | D4: 12 | E4: 150 | F4: =D4*E4 | G4: 0 | H4: =F4*(1-G4)
A5: 2024-05-01 | B5: P002 | C5: West | D5: 3 | E5: 800 | F5: =D5*E5 | G5: 0.1 | H5: =F5*(1-G5)
A6: 2024-05-12 | B6: P007 | C6: North | D6: 2 | E6: 500 | F6: =D6*E6 | G6: 0 | H6: =F6*(1-G6)
A7: 2024-05-25 | B7: P001 | C7: East | D7: 5 | E7: 1200 | F7: =D7*E7 | G7: 0.05 | H7: =F7*(1-G7)
A8: 2024-06-03 | B8: P006 | C8: South | D8: 25 | E8: 45 | F8: =D8*E8 | G8: 0 | H8: =F8*(1-G8)
A9: 2024-06-14 | B9: P010 | C9: North | D9: 3 | E9: 450 | F9: =D9*E9 | G9: 0.1 | H9: =F9*(1-G9)
A10: 2024-06-20 | B10: P002 | C10: East | D10: 7 | E10: 800 | F10: =D10*E10 | G10: 0 | H10: =F10*(1-G10)
A11: 2024-04-08 | B11: P008 | C11: West | D11: 1 | E11: 180 | F11: =D11*E11 | G11: 0 | H11: =F11*(1-G11)
A12: 2024-04-20 | B12: P009 | C12: North | D12: 6 | E12: 95 | F12: =D12*E12 | G12: 0 | H12: =F12*(1-G12)
A13: 2024-05-05 | B13: P001 | C13: South | D13: 3 | E13: 1200 | F13: =D13*E13 | G13: 0.1 | H13: =F13*(1-G13)
... A16: 2024-06-10 | B16: P004 | C16: North | D16: 2 | E16: 275 | F16: =D16*E16 | G16: 0.15 | H16: =F16*(1-G16)
A18: TOTAL_QTY | D18: =SUM(D2:D16)
A19: TOTAL_REVENUE | F19: =SUM(F2:F16)
A20: TOTAL_NET_REV | H20: =SUM(H2:H16)
A21: AVG_DISCOUNT | G21: =AVERAGE(G2:G16)
A22: NORTH_REVENUE | F22: =SUMIFS(F2:F16,C2:C16,"North")
A23: SOUTH_REVENUE | F23: =SUMIFS(F2:F16,C2:C16,"South")
A24: EAST_REVENUE | F24: =SUMIFS(F2:F16,C2:C16,"East")
A25: WEST_REVENUE | F25: =SUMIFS(F2:F16,C2:C16,"West")

Sheet Annual Summary
A1: Metric | B1: Q1 | C1: Q2 | D1: Total / Change
A2: Total Units Sold | B2: ='Q1 Sales'!D22 | C2: ='Q2 Sales'!D18 | D2: =B2+C2
A3: Total Revenue | B3: ='Q1 Sales'!F23 | C3: ='Q2 Sales'!F19 | D3: =B3+C3
A4: Total Net Revenue | B4: ='Q1 Sales'!H24 | C4: ='Q2 Sales'!H20 | D4: =B4+C4
A5: Average Discount | B5: ='Q1 Sales'!G25 | C5: ='Q2 Sales'!G21 | D5: =AVERAGE(B5,C5)
A6: Revenue Growth Q1->Q2 | D6: =IFERROR((C3-B3)/B3,0)
A8: Region | B8: Q1 Revenue | C8: Q2 Revenue | D8: Total
A9: North | B9: ='Q1 Sales'!F26 | C9: ='Q2 Sales'!F22 | D9: =B9+C9
A10: South | B10: ='Q1 Sales'!F27 | C10: ='Q2 Sales'!F23 | D10: =B10+C10
A11: East | B11: ='Q1 Sales'!F28 | C11: ='Q2 Sales'!F24 | D11: =B11+C11
A12: West | B12: ='Q1 Sales'!F29 | C12: ='Q2 Sales'!F25 | D12: =B12+C12
A13: TOTAL | B13: =SUM(B9:B12) | C13: =SUM(C9:C12) | D13: =SUM(D9:D12)
A15: Category Analysis
A16: Avg Product Margin | B16: ='Products'!F13
A17: Active Products | B17: ='Products'!D17
A18: Revenue per Active Product | B18: =IF(B17>0,D3/B17,0)

Sheet Pivot Analysis
A1: Category | B1: Product Count | C1: Total Q1 Revenue | D1: Total Q2 Revenue | E1: Combined Revenue
A2: Electronics | B2: =COUNTIF(Products!B2:B11,"Electronics") | C2: =SUMIFS('Q1 Sales'!F2:F20,'Q1 Sales'!B2:B20,"P001")+SUMIFS('Q1 Sales'!F2:F20,'Q1 Sales'!B2:B20,"P002")+SUMIFS('Q1 Sales'!F2:F20,'Q1 Sales'!B2:B20,"P007")+SUMIFS('Q1 Sales'!F2:F20,'Q1 Sales'!B2:B20,"P010") | D2: =SUMIFS('Q2 Sales'!F2:F16,'Q2 Sales'!B2:B16,"P001")+SUMIFS('Q2 Sales'!F2:F16,'Q2 Sales'!B2:B16,"P002")+SUMIFS('Q2 Sales'!F2:F16,'Q2 Sales'!B2:B16,"P007")+SUMIFS('Q2 Sales'!F2:F16,'Q2 Sales'!B2:B16,"P010") | E2: =C2+D2
A3: Furniture | B3: =COUNTIF(Products!B2:B11,"Furniture") | C3: =SUMIFS('Q1 Sales'!F2:F20,'Q1 Sales'!B2:B20,"P003")+SUMIFS('Q1 Sales'!F2:F20,'Q1 Sales'!B2:B20,"P004")+SUMIFS('Q1 Sales'!F2:F20,'Q1 Sales'!B2:B20,"P008") | D3: =SUMIFS('Q2 Sales'!F2:F16,'Q2 Sales'!B2:B16,"P003")+SUMIFS('Q2 Sales'!F2:F16,'Q2 Sales'!B2:B16,"P004")+SUMIFS('Q2 Sales'!F2:F16,'Q2 Sales'!B2:B16,"P008") | E3: =C3+D3
A4: Clothing | B4: =COUNTIF(Products!B2:B11,"Clothing") | C4: =SUMIFS('Q1 Sales'!F2:F20,'Q1 Sales'!B2:B20,"P005")+SUMIFS('Q1 Sales'!F2:F20,'Q1 Sales'!B2:B20,"P006")+SUMIFS('Q1 Sales'!F2:F20,'Q1 Sales'!B2:B20,"P009") | D4: =SUMIFS('Q2 Sales'!F2:F16,'Q2 Sales'!B2:B16,"P005")+SUMIFS('Q2 Sales'!F2:F16,'Q2 Sales'!B2:B16,"P006")+SUMIFS('Q2 Sales'!F2:F16,'Q2 Sales'!B2:B16,"P009") | E4: =C4+D4
A6: Grand Total | B6: =SUM(B2:B4) | C6: =SUM(C2:C4) | D6: =SUM(D2:D4) | E6: =C6+D6
A8: Discount Impact | C8: Q1 Revenue | D8: Q2 Revenue | E8: Combined
A9: With Discount | C9: =SUMIFS('Q1 Sales'!F2:F20,'Q1 Sales'!G2:G20,">0") | D9: =SUMIFS('Q2 Sales'!F2:F16,'Q2 Sales'!G2:G16,">0") | E9: =C9+D9
A10: Without Discount | C10: =SUMIFS('Q1 Sales'!F2:F20,'Q1 Sales'!G2:G20,"0") | D10: =SUMIFS('Q2 Sales'!F2:F16,'Q2 Sales'!G2:G16,"0") | E10: =C10+D10
A12: Top Region by Q1 Revenue | B12: =IF('Annual Summary'!D9>='Annual Summary'!D10,IF('Annual Summary'!D9>='Annual Summary'!D11,IF('Annual Summary'!D9>='Annual Summary'!D12,"North","West"),"East"),IF('Annual Summary'!D10>='Annual Summary'!D11,IF('Annual Summary'!D10>='Annual Summary'!D12,"South","West"),"East"))
